README.rst
setup.py
conflate/__init__.py
conflate/__main__.py
conflate/conflate.py
conflate/conflator.py
conflate/data.py
conflate/dataset.py
conflate/geocoder.py
conflate/osm.py
conflate/places.bin
conflate/profile.py
conflate/version.py
osm_conflate.egg-info/PKG-INFO
osm_conflate.egg-info/SOURCES.txt
osm_conflate.egg-info/dependency_links.txt
osm_conflate.egg-info/entry_points.txt
osm_conflate.egg-info/requires.txt
osm_conflate.egg-info/top_level.txt