Metadata-Version: 1.1
Name: osm-conflate
Version: 1.4.1
Summary: Command-line script for merging points from a third-party source with OpenStreetMap data
Home-page: https://github.com/mapsme/osm_conflate
Author: Ilya Zverev
Author-email: ilya@zverev.info
License: Apache License 2.0
Platform: UNKNOWN
Classifier: Development Status :: 5 - Production/Stable
Classifier: Environment :: Console
Classifier: Intended Audience :: Information Technology
Classifier: Intended Audience :: Developers
Classifier: Topic :: Software Development :: Libraries :: Python Modules
Classifier: Natural Language :: English
Classifier: Operating System :: OS Independent
Classifier: Topic :: Utilities
Classifier: License :: OSI Approved :: Apache Software License
Classifier: Programming Language :: Python :: 3 :: Only
